{
  "collected_at": "2026-02-28T06:00:00Z",
  "period": "2026-02",
  "is_mtd": true,
  "periods": {
    "current": "2026-02",
    "prev_month": "2025-12",
    "yoy": "2025-02"
  },
  "storage_config": {
    "include_efs": false,
    "include_ebs": false
  },
  "storage_metrics": {
    "total_cost_usd": 3900.0,
    "prev_month_cost_usd": 4200.0,
    "total_volume_bytes": 182000000000000,
    "hot_tier_percentage": 61.8,
    "cost_per_tb_usd": 21.43
  },
  "cost_centers": [
    {
      "name": "Engineering",
      "current_cost_usd": 14200.0,
      "prev_month_cost_usd": 14200.0,
      "yoy_cost_usd": 11500.0,
      "workloads": [
        {
          "name": "data-pipeline",
          "current_cost_usd": 4700.0,
          "prev_month_cost_usd": 4800.0,
          "yoy_cost_usd": 3400.0
        },
        {
          "name": "ml-training",
          "current_cost_usd": 4050.0,
          "prev_month_cost_usd": 4100.0,
          "yoy_cost_usd": 3600.0
        },
        {
          "name": "web-platform",
          "current_cost_usd": 2950.0,
          "prev_month_cost_usd": 3000.0,
          "yoy_cost_usd": 2900.0
        },
        {
          "name": "monitoring",
          "current_cost_usd": 1600.0,
          "prev_month_cost_usd": 1500.0,
          "yoy_cost_usd": 1100.0
        },
        {
          "name": "Untagged",
          "current_cost_usd": 900.0,
          "prev_month_cost_usd": 800.0,
          "yoy_cost_usd": 500.0
        }
      ]
    },
    {
      "name": "Data Science",
      "current_cost_usd": 6600.0,
      "prev_month_cost_usd": 6800.0,
      "yoy_cost_usd": 5400.0,
      "workloads": [
        {
          "name": "analytics-platform",
          "current_cost_usd": 3300.0,
          "prev_month_cost_usd": 3400.0,
          "yoy_cost_usd": 2700.0
        },
        {
          "name": "data-lake",
          "current_cost_usd": 2350.0,
          "prev_month_cost_usd": 2400.0,
          "yoy_cost_usd": 1900.0
        },
        {
          "name": "batch-jobs",
          "current_cost_usd": 950.0,
          "prev_month_cost_usd": 1000.0,
          "yoy_cost_usd": 800.0
        }
      ]
    },
    {
      "name": "Platform",
      "current_cost_usd": 1400.0,
      "prev_month_cost_usd": 1200.0,
      "yoy_cost_usd": 850.0,
      "workloads": [
        {
          "name": "shared-services",
          "current_cost_usd": 850.0,
          "prev_month_cost_usd": 750.0,
          "yoy_cost_usd": 530.0
        },
        {
          "name": "ci-cd",
          "current_cost_usd": 550.0,
          "prev_month_cost_usd": 450.0,
          "yoy_cost_usd": 320.0
        }
      ]
    }
  ],
  "tagging_coverage": {
    "tagged_cost_usd": 21300.0,
    "untagged_cost_usd": 900.0,
    "tagged_percentage": 95.9
  },
  "mtd_comparison": {
    "prior_partial_start": "2026-01-01",
    "prior_partial_end_exclusive": "2026-01-28",
    "cost_centers": [
      {
        "name": "Engineering",
        "prior_partial_cost_usd": 13500.0,
        "workloads": [
          {
            "name": "data-pipeline",
            "prior_partial_cost_usd": 4500.0
          },
          {
            "name": "ml-training",
            "prior_partial_cost_usd": 3800.0
          },
          {
            "name": "web-platform",
            "prior_partial_cost_usd": 2800.0
          },
          {
            "name": "monitoring",
            "prior_partial_cost_usd": 1500.0
          },
          {
            "name": "Untagged",
            "prior_partial_cost_usd": 900.0
          }
        ]
      },
      {
        "name": "Data Science",
        "prior_partial_cost_usd": 6200.0,
        "workloads": [
          {
            "name": "analytics-platform",
            "prior_partial_cost_usd": 3100.0
          },
          {
            "name": "data-lake",
            "prior_partial_cost_usd": 2200.0
          },
          {
            "name": "batch-jobs",
            "prior_partial_cost_usd": 900.0
          }
        ]
      },
      {
        "name": "Platform",
        "prior_partial_cost_usd": 1100.0,
        "workloads": [
          {
            "name": "shared-services",
            "prior_partial_cost_usd": 680.0
          },
          {
            "name": "ci-cd",
            "prior_partial_cost_usd": 420.0
          }
        ]
      }
    ]
  }
}
